robusta/__init__.py
robusta/correlations/__init__.py
robusta/correlations/api.py
robusta/correlations/models.py
robusta/correlations/results.py
robusta/correlations/tests/__init__.py
robusta/correlations/tests/test_correlations.py
robusta/groupwise/__init__.py
robusta/groupwise/api.py
robusta/groupwise/models.py
robusta/groupwise/reports.py
robusta/groupwise/results.py
robusta/groupwise/tests/__init__.py
robusta/groupwise/tests/test_output.py
robusta/groupwise/tests/test_vs_r_output.py
robusta/misc/__init__.py
robusta/misc/base.py
robusta/misc/datasets.py
robusta/misc/formula_tools.py
robusta/misc/pyrio.py
robusta/misc/utils.py
robusta/regressions/__init__.py
robusta/regressions/api.py
robusta/regressions/models.py
robusta/regressions/results.py
robusta/regressions/tests/__init__.py
robusta/regressions/tests/test_regressions.py
robusta/tests/__init__.py
robusta/tests/test_formula_tools.py
robusta_stats-0.0.3.dist-info/LICENSE.txt
robusta_stats-0.0.3.dist-info/METADATA
robusta_stats-0.0.3.dist-info/WHEEL
robusta_stats-0.0.3.dist-info/top_level.txt
robusta_stats-0.0.3.dist-info/RECORD
