Metadata-Version: 2.1
Name: robusta-stats
Version: 0.0.3
Summary: Statistical analysis package in Python
Home-page: https://github.com/EitanHemed/robusta
Author: Eitan Hemed
Author-email: Eitan.Hemed@gmail.com
License: UNKNOWN
Download-URL: https://github.com/EitanHemed/robusta
Platform: UNKNOWN
Classifier: Programming Language :: Python :: 3
Classifier: License :: OSI Approved :: GNU General Public License (GPL)
Classifier: Operating System :: OS Independent
Requires-Python: >=3.7.10
License-File: LICENSE.txt
Requires-Dist: pandas (~=1.2.4)
Requires-Dist: rpy2 (>=3.4.3)
Requires-Dist: numpy (~=1.20.2)
Requires-Dist: patsy (~=0.5.1)
Requires-Dist: tzlocal
Requires-Dist: pytest (~=6.2.3)
Requires-Dist: pytest-cov
Requires-Dist: tqdm
